{
    "baseURL": "https://flowfuse.com",
    "appURL": "https://app.flowfuse.com",
    "jobBoard": "https://boards.greenhouse.io/flowfuse",
    "openings": {
        "pgm": "https://boards.greenhouse.io/flowfuse/jobs/5155365004",
        "repeu": "https://boards.greenhouse.io/flowfuse/jobs/5171314004",
        "d2fe": "https://boards.greenhouse.io/flowfuse/jobs/5185319004"
    },
    "messaging": {
        "tagLine": "The Fastest Way to Build and Operate Industrial Data Solutions",
        "subtitle": "Connect, collect, transform, visualise, and interact with your Industrial Data in a single platform. FlowFuse helps manage, scale and secure your Node-RED solutions.",
        "title": "Enterprise-ready Node-RED for Rapid Industrial Process Improvement",
        "keywords": "Node-RED, Application Developement, IoT, IIoT, Low-Code, Open-Source, open source"
    }
}
