{
    "baseURL": "https://flowfuse.com",
    "appURL": "https://app.flowfuse.com",
    "jobBoard": "https://boards.greenhouse.io/flowfuse",
    "openings": {
        "em": "https://job-boards.greenhouse.io/flowfuse/jobs/5566913004"
    },
    "messaging": {
        "tagLine": "The edge-native platform for industrial applications",
        "subtitle": "Build, deploy, and govern operational applications across every plant and production line, distributed to the edge and accelerated by AI.",
        "title": "Build workflows and integrations that optimize your industrial operations",
        "keywords": "Node-RED, Application Development, IoT, IIoT, Low-Code, open source, Integration, Workflow, Automation, Data Processing, Data Integration, Data Transformation, Data Visualization, Industrial Automation, Industrial IoT, Industry 4.0"
    },
    "organization": {
        "legalName": "FlowFuse Inc.",
        "alternateName": ["FlowForge", "Flow Fuse"],
        "foundingDate": "2021",
        "founders": ["nick-oleary"],
        "logo": "https://flowfuse.com/handbook/images/logos/ff-logo--wordmark--light.png",
        "sameAs": [
            "https://www.linkedin.com/company/flowfuse",
            "https://github.com/FlowFuse",
            "https://www.youtube.com/@FlowFuseInc",
            "https://twitter.com/FlowFuseInc",
            "https://www.crunchbase.com/organization/flowforge",
            "https://www.g2.com/sellers/flowfuse",
            "https://www.facebook.com/FlowFuse",
            "https://www.reddit.com/r/FlowFuse/"
        ]
    }
}
